pylook/__init__.py
pylook/_version.py
pylook/axes.py
pylook/coast.py
pylook/figure.py
pylook/figures_set.py
pylook/logger.py
pylook/parser.py
pylook/appli/__init__.py
pylook/appli/data_header.py
pylook/appli/data_look.py
pylook/appli/pylook.py
pylook/data/__init__.py
pylook/data/data_store.py
pylook/data/demo_dataset.py
pylook/gshhs_backup/binned_GSHHS_l.nc
pylook/gshhs_backup/binned_border_l.nc
pylook/gshhs_backup/binned_river_l.nc
pylook/pylook_object/__init__.py
pylook/pylook_object/base.py
pylook/pylook_object/method.py
pylook/pylook_object/plot_object.py
pylook/ui/__init__.py
pylook/ui/data_tree.py
pylook/ui/figures_tree.py
pylook/ui/pylook.py
pylook/ui/resource_rc.py
pylook/ui/tabs.py
pylook_map-0.1.1.dist-info/LICENSE
pylook_map-0.1.1.dist-info/METADATA
pylook_map-0.1.1.dist-info/WHEEL
pylook_map-0.1.1.dist-info/entry_points.txt
pylook_map-0.1.1.dist-info/top_level.txt
pylook_map-0.1.1.dist-info/RECORD
