Metadata-Version: 2.1
Name: pylook-map
Version: 0.1.1
Summary: Python Distribution Utilities
Home-page: UNKNOWN
Author: Antoine Delepoulle
Author-email: delepoulle.a@gmail.com
License: UNKNOWN
Platform: UNKNOWN
Requires-Python: >=3.7
Requires-Dist: numpy
Requires-Dist: matplotlib
Requires-Dist: netCDF4
Requires-Dist: pyproj
Requires-Dist: numba
Requires-Dist: zarr
